pyMechkar/__init__.py
pyMechkar/analysis.py
pyMechkar/exploreData.py
pyMechkar-0.1.6.dist-info/LICENSE.txt
pyMechkar-0.1.6.dist-info/METADATA
pyMechkar-0.1.6.dist-info/WHEEL
pyMechkar-0.1.6.dist-info/top_level.txt
pyMechkar-0.1.6.dist-info/RECORD
