Metadata-Version: 2.1
Name: pyMechkar
Version: 0.1.6
Summary: Useful Tools for Scientific Research
Home-page: https://github.com/karpatit/pyMechkar
Author: Tomas Karpati
Author-email: karpati@it4biotech.com
License: UNKNOWN
Platform: UNKNOWN
Classifier: Programming Language :: Python :: 3
Classifier: License :: OSI Approved :: MIT License
Classifier: Operating System :: OS Independent
Requires-Python: >=3.4
